aes_dfa-0.1.1.dist-info/METADATA
aes_dfa-0.1.1.dist-info/WHEEL
aes_dfa/__init__.py
aes_dfa/aes_dfa.cpython-312-x86_64-linux-gnu.so
aes_dfa-0.1.1.dist-info/RECORD
