Metadata-Version: 2.4
Name: aes-dfa
Version: 0.1.1
Classifier: Programming Language :: Rust
Classifier: Programming Language :: Python :: Implementation :: CPython
Classifier: Programming Language :: Python :: Implementation :: PyPy
Summary: Homemade implementation of differential fault against AES using a single fault, written in Rust
Requires-Python: >=3.8
